httpx_retries/__init__.py
httpx_retries/py.typed
httpx_retries/retry.py
httpx_retries/transport.py
httpx_retries-0.4.4.dist-info/METADATA
httpx_retries-0.4.4.dist-info/WHEEL
httpx_retries-0.4.4.dist-info/licenses/LICENSE
httpx_retries-0.4.4.dist-info/RECORD
