Metadata-Version: 2.4
Name: httpx-retries
Version: 0.4.4
Dynamic: License
Dynamic: License-Expression
Summary: A retry layer for HTTPX.
Project-URL: Changelog, https://github.com/will-ockmore/httpx-retries/blob/master/CHANGELOG.md
Project-URL: Documentation, https://will-ockmore.github.io/httpx-retries
Project-URL: Homepage, https://github.com/will-ockmore/httpx-retries
Project-URL: Source, https://github.com/will-ockmore/httpx-retries
Author-email: Will Ockmore <will.ockmore@gmail.com>
License-File: LICENSE
Classifier: Development Status :: 4 - Beta
Classifier: Environment :: Web Environment
Classifier: Framework :: AsyncIO
Classifier: Framework :: Trio
Classifier: Intended Audience :: Developers
Classifier: License :: OSI Approved :: MIT License
Classifier: Operating System :: OS Independent
Classifier: Programming Language :: Python :: 3
Classifier: Programming Language :: Python :: 3.9
Classifier: Programming Language :: Python :: 3.10
Classifier: Programming Language :: Python :: 3.11
Classifier: Programming Language :: Python :: 3.12
Classifier: Topic :: Internet :: WWW/HTTP
Requires-Python: >=3.9
Requires-Dist: httpx>=0.20.0
